README.md
setup.py
mints/__init__.py
mints/cli.py
mints/command.py
mints.egg-info/PKG-INFO
mints.egg-info/SOURCES.txt
mints.egg-info/dependency_links.txt
mints.egg-info/top_level.txt
mints/args/__init__.py
mints/args/arg.py
mints/args/flag.py
mints/args/opt.py
mints/args/typed.py
mints/parsers/__init__.py
mints/parsers/parser.py
mints/parsers/standard.py