Metadata-Version: 2.1
Name: mints
Version: 0.0.1
Summary: Clean and elegant CLI development kit
Home-page: https://github.com/candy-kingdom/mints
Author: Candy Kingdom
Author-email: candy.kingdom.github@gmail.com
License: MIT
Platform: UNKNOWN
Classifier: Development Status :: 3 - Alpha
Classifier: Intended Audience :: Developers
Classifier: License :: OSI Approved :: MIT License
Classifier: Natural Language :: English
Classifier: Programming Language :: Python :: 3.8
Classifier: Programming Language :: Python :: 3.7
Classifier: Topic :: Software Development :: Libraries :: Python Modules
